MANIFEST.in
README.md
setup.cfg
setup.py
mechanical_components/LibSvg.py
mechanical_components/__init__.py
mechanical_components/beams.py
mechanical_components/bearings.py
mechanical_components/clutches.py
mechanical_components/fasteners.py
mechanical_components/load.py
mechanical_components/meshes.py
mechanical_components/retainers.py
mechanical_components/springs.py
mechanical_components/tools.py
mechanical_components/wheels.py
mechanical_components/wires.py
mechanical_components.egg-info/PKG-INFO
mechanical_components.egg-info/SOURCES.txt
mechanical_components.egg-info/dependency_links.txt
mechanical_components.egg-info/not-zip-safe
mechanical_components.egg-info/requires.txt
mechanical_components.egg-info/top_level.txt
mechanical_components/assets/logos/bearings.RadialBallBearing.png
mechanical_components/assets/logos/bearings.RadialRollerBearing.png
mechanical_components/assets/logos/bearings.TaperedRollerBearing.png
mechanical_components/assets/logos/bearings.jpg
mechanical_components/assets/logos/mechanical_components.jpg
mechanical_components/catalogs/ISO_bearings.py
mechanical_components/catalogs/SKF.csv
mechanical_components/catalogs/SKF_raw.csv
mechanical_components/catalogs/__init__.py
mechanical_components/catalogs/ferroflex.csv
mechanical_components/catalogs/radial_clearance_iso.csv
mechanical_components/catalogs/roller_iso.csv
mechanical_components/catalogs/roymech_external_circlips.json
mechanical_components/catalogs/roymech_internal_circlips.json
mechanical_components/catalogs/rules_rlts_SKF.csv
mechanical_components/catalogs/schaeffler.json
mechanical_components/catalogs/serie_rlts_iso.csv
mechanical_components/models/__init__.py
mechanical_components/models/catalogs.py
mechanical_components/models/optimizer_bearing.py
mechanical_components/optimization/__init__.py
mechanical_components/optimization/bearings.py
mechanical_components/optimization/common.py
mechanical_components/optimization/meshes.py
mechanical_components/optimization/wires.py
scripts/compilation_test.py
scripts/bearings/bearing0.py
scripts/bearings/bearing1.py
scripts/bearings/bearing3.py
scripts/bearings/bearing_aeronautics.py
scripts/bearings/bearing_combination1.py
scripts/bearings/bearing_combination2.py
scripts/bearings/bearing_snr.py
