Metadata-Version: 1.0
Name: mechanical-components
Version: 0.3.post4
Summary: Design of elementary components by AI
Home-page: UNKNOWN
Author: DessiA Technologies
Author-email: root@dessia.tech
License: UNKNOWN
Platform: UNKNOWN
